{
  "update_time": 1587697212,
  "android": [
    { "percentage": 21.4836366919, "sdkVer": "2.11.0" },
    { "percentage": 72.9663391128, "sdkVer": "2.10.4" },
    { "percentage": 1.15365935958, "sdkVer": "2.10.3" },
    { "percentage": 0.00057511978268, "sdkVer": "2.10.2" },
    { "percentage": 0.0416560201414, "sdkVer": "2.10.1" },
    { "percentage": 0.000102578741567, "sdkVer": "2.10.0" },
    { "percentage": 1.09090291744, "sdkVer": "2.9.5" },
    { "percentage": 0.000139160131022, "sdkVer": "2.9.4" },
    { "percentage": 0.0685261192252, "sdkVer": "2.9.3" },
    { "percentage": 8.04539149541e-6, "sdkVer": "2.9.2" },
    { "percentage": 0.00291356310452, "sdkVer": "2.9.1" },
    { "percentage": 9.05106543234e-6, "sdkVer": "2.9.0" },
    { "percentage": 1.34313725466, "sdkVer": "2.8.3" },
    { "percentage": 1.35765981485e-5, "sdkVer": "2.8.2" },
    { "percentage": 0.00555659992, "sdkVer": "2.8.1" },
    { "percentage": 1.4079435117e-5, "sdkVer": "2.8.0" },
    { "percentage": 0.622163700938, "sdkVer": "2.7.7" },
    { "percentage": 5.02836968463e-7, "sdkVer": "2.7.6" },
    { "percentage": 3.01702181078e-6, "sdkVer": "2.7.5" },
    { "percentage": 3.26844029501e-6, "sdkVer": "2.7.4" },
    { "percentage": 3.77127726347e-6, "sdkVer": "2.7.3" },
    { "percentage": 3.51985877924e-6, "sdkVer": "2.7.2" },
    { "percentage": 0.0104700713573, "sdkVer": "2.7.1" },
    { "percentage": 4.65124195829e-6, "sdkVer": "2.7.0" },
    { "percentage": 0.625664829041, "sdkVer": "2.6.6" },
    { "percentage": 2.26276635808e-6, "sdkVer": "2.6.5" },
    { "percentage": 2.26276635808e-6, "sdkVer": "2.6.4" },
    { "percentage": 3.87184465717e-5, "sdkVer": "2.6.2" },
    { "percentage": 1.25709242116e-6, "sdkVer": "2.6.1" },
    { "percentage": 3.26844029501e-6, "sdkVer": "2.6.0" },
    { "percentage": 0.195440787264, "sdkVer": "2.5.2" },
    { "percentage": 0.00543101638713, "sdkVer": "2.5.1" },
    { "percentage": 7.54255452695e-7, "sdkVer": "2.5.0" },
    { "percentage": 0.173594658041, "sdkVer": "2.4.4" },
    { "percentage": 2.51418484232e-7, "sdkVer": "2.4.3" },
    { "percentage": 5.02836968463e-7, "sdkVer": "2.4.1" },
    { "percentage": 0.00104137536169, "sdkVer": "2.4.0" },
    { "percentage": 0.0291202945176, "sdkVer": "2.3.2" },
    { "percentage": 5.02836968463e-7, "sdkVer": "2.3.1" },
    { "percentage": 0.00077889446415, "sdkVer": "2.3.0" },
    { "percentage": 0.0744227626451, "sdkVer": "2.2.5" },
    { "percentage": 5.02836968463e-7, "sdkVer": "2.2.3" },
    { "percentage": 1.50851090539e-6, "sdkVer": "2.2.2" },
    { "percentage": 2.51418484232e-7, "sdkVer": "2.2.1" },
    { "percentage": 0.000104967217167, "sdkVer": "2.2.0" },
    { "percentage": 0.0315549054097, "sdkVer": "2.0.9" },
    { "percentage": 2.51418484232e-7, "sdkVer": "2.0.8" },
    { "percentage": 0.0357808730019, "sdkVer": "1.9.97" },
    { "percentage": 2.51418484232e-7, "sdkVer": "1.9.96" },
    { "percentage": 0.000443753624669, "sdkVer": "1.9.95" },
    { "percentage": 0.0122165498581, "sdkVer": "1.9.9" },
    { "percentage": 2.51418484232e-7, "sdkVer": "1.9.8" },
    { "percentage": 0.000337152187355, "sdkVer": "1.9.6" },
    { "percentage": 0.00103119291308, "sdkVer": "1.9.4" },
    { "percentage": 7.54255452695e-7, "sdkVer": "1.9.2" },
    { "percentage": 0.000228036565198, "sdkVer": "1.7.4" },
    { "percentage": 0.000171467406246, "sdkVer": "1.7.3" },
    { "percentage": 6.33574580264e-5, "sdkVer": "1.6.8" },
    { "percentage": 4.55067456459e-5, "sdkVer": "1.6.6" },
    { "percentage": 8.04539149541e-6, "sdkVer": "1.6.3" },
    { "percentage": 1.25709242116e-5, "sdkVer": "1.5.8" },
    { "percentage": 0.000166187618077, "sdkVer": "1.4.4" },
    { "percentage": 0.000145068465402, "sdkVer": "1.2.5" },
    { "percentage": 9.5539024008e-6, "sdkVer": "1.2.4" },
    { "percentage": 0.0018192641519, "sdkVer": "1.1.1" },
    { "percentage": 0.000243750220463, "sdkVer": "1.0.1" }
  ],
  "iOS": [
    { "percentage": 23.3407698104, "sdkVer": "2.11.0" },
    { "percentage": 68.2176835018, "sdkVer": "2.10.4" },
    { "percentage": 0.00480033141714, "sdkVer": "2.10.3" },
    { "percentage": 0.00109246265894, "sdkVer": "2.10.2" },
    { "percentage": 0.00101030330503, "sdkVer": "2.10.1" },
    { "percentage": 0.000104838758887, "sdkVer": "2.10.0" },
    { "percentage": 3.30674454095, "sdkVer": "2.9.5" },
    { "percentage": 0.000510928482088, "sdkVer": "2.9.4" },
    { "percentage": 0.00300737468351, "sdkVer": "2.9.3" },
    { "percentage": 2.78143646028e-5, "sdkVer": "2.9.2" },
    { "percentage": 6.07636888246e-5, "sdkVer": "2.9.1" },
    { "percentage": 2.99539311107e-5, "sdkVer": "2.9.0" },
    { "percentage": 1.36197957281, "sdkVer": "2.8.3" },
    { "percentage": 2.6530624698e-5, "sdkVer": "2.8.2" },
    { "percentage": 0.000108689978602, "sdkVer": "2.8.1" },
    { "percentage": 4.1935503555e-5, "sdkVer": "2.8.0" },
    { "percentage": 1.01397480116, "sdkVer": "2.7.7" },
    { "percentage": 1.71165320633e-6, "sdkVer": "2.7.6" },
    { "percentage": 8.55826603163e-6, "sdkVer": "2.7.5" },
    { "percentage": 5.13495961898e-6, "sdkVer": "2.7.4" },
    { "percentage": 1.15536591427e-5, "sdkVer": "2.7.3" },
    { "percentage": 1.58327921585e-5, "sdkVer": "2.7.2" },
    { "percentage": 0.000344470207773, "sdkVer": "2.7.1" },
    { "percentage": 8.55826603163e-6, "sdkVer": "2.7.0" },
    { "percentage": 1.14867805728, "sdkVer": "2.6.6" },
    { "percentage": 5.99078622214e-6, "sdkVer": "2.6.5" },
    { "percentage": 4.7070463174e-6, "sdkVer": "2.6.4" },
    { "percentage": 4.66425498724e-5, "sdkVer": "2.6.2" },
    { "percentage": 8.13035273005e-6, "sdkVer": "2.6.1" },
    { "percentage": 5.99078622214e-6, "sdkVer": "2.6.0" },
    { "percentage": 0.420953291731, "sdkVer": "2.5.2" },
    { "percentage": 3.42330641265e-6, "sdkVer": "2.5.1" },
    { "percentage": 2.56747980949e-6, "sdkVer": "2.5.0" },
    { "percentage": 0.626510004412, "sdkVer": "2.4.4" },
    { "percentage": 1.71165320633e-6, "sdkVer": "2.4.3" },
    { "percentage": 8.55826603163e-7, "sdkVer": "2.4.2" },
    { "percentage": 8.55826603163e-7, "sdkVer": "2.4.0" },
    { "percentage": 0.146259054827, "sdkVer": "2.3.2" },
    { "percentage": 0.138370473113, "sdkVer": "2.2.5" },
    { "percentage": 6.58986484435e-5, "sdkVer": "2.2.4" },
    { "percentage": 0.0544160229089, "sdkVer": "2.1.3" },
    { "percentage": 0.0840841079341, "sdkVer": "2.0.9" },
    { "percentage": 0.0695414743799, "sdkVer": "1.9.97" },
    { "percentage": 0.0325265458798, "sdkVer": "1.9.9" },
    { "percentage": 1.71165320633e-6, "sdkVer": "1.9.6" },
    { "percentage": 0.00922238747568, "sdkVer": "1.9.4" },
    { "percentage": 0.000173732800442, "sdkVer": "1.7.4" },
    { "percentage": 0.000303818444123, "sdkVer": "1.6.8" },
    { "percentage": 0.000307241750535, "sdkVer": "1.5.8" },
    { "percentage": 0.000109545805205, "sdkVer": "1.4.4" },
    { "percentage": 8.55826603163e-5, "sdkVer": "1.3.0" },
    { "percentage": 9.58525795542e-5, "sdkVer": "1.2.5" },
    { "percentage": 0.0110735404183, "sdkVer": "1.1.1" }
  ],
  "total": [
    { "percentage": 21.9053297741, "sdkVer": "2.11.0" },
    { "percentage": 71.8880775703, "sdkVer": "2.10.4" },
    { "percentage": 0.892791735291, "sdkVer": "2.10.3" },
    { "percentage": 0.000692591120559, "sdkVer": "2.10.2" },
    { "percentage": 0.0324267314917, "sdkVer": "2.10.1" },
    { "percentage": 0.000103091916234, "sdkVer": "2.10.0" },
    { "percentage": 1.5940467549, "sdkVer": "2.9.5" },
    { "percentage": 0.000223576342369, "sdkVer": "2.9.4" },
    { "percentage": 0.053648994342, "sdkVer": "2.9.3" },
    { "percentage": 1.25342669125e-5, "sdkVer": "2.9.2" },
    { "percentage": 0.00226578736537, "sdkVer": "2.9.1" },
    { "percentage": 1.37974100897e-5, "sdkVer": "2.9.0" },
    { "percentage": 1.34741571759, "sdkVer": "2.8.3" },
    { "percentage": 1.65180261637e-5, "sdkVer": "2.8.2" },
    { "percentage": 0.00431956100668, "sdkVer": "2.8.1" },
    { "percentage": 2.04046205552e-5, "sdkVer": "2.8.0" },
    { "percentage": 0.711130953126, "sdkVer": "2.7.7" },
    { "percentage": 7.77318878293e-7, "sdkVer": "2.7.6" },
    { "percentage": 4.27525383061e-6, "sdkVer": "2.7.5" },
    { "percentage": 3.69226467189e-6, "sdkVer": "2.7.4" },
    { "percentage": 5.53839700784e-6, "sdkVer": "2.7.3" },
    { "percentage": 6.31571588613e-6, "sdkVer": "2.7.2" },
    { "percentage": 0.00817088455404, "sdkVer": "2.7.1" },
    { "percentage": 5.53839700784e-6, "sdkVer": "2.7.0" },
    { "percentage": 0.744423715013, "sdkVer": "2.6.6" },
    { "percentage": 3.10927551317e-6, "sdkVer": "2.6.5" },
    { "percentage": 2.81778093381e-6, "sdkVer": "2.6.4" },
    { "percentage": 4.0517746531e-5, "sdkVer": "2.6.2" },
    { "percentage": 2.81778093381e-6, "sdkVer": "2.6.1" },
    { "percentage": 3.88659439147e-6, "sdkVer": "2.6.0" },
    { "percentage": 0.246647166677, "sdkVer": "2.5.2" },
    { "percentage": 0.00419859075624, "sdkVer": "2.5.1" },
    { "percentage": 1.16597831744e-6, "sdkVer": "2.5.0" },
    { "percentage": 0.276436649544, "sdkVer": "2.4.4" },
    { "percentage": 5.8298915872e-7, "sdkVer": "2.4.3" },
    { "percentage": 1.94329719573e-7, "sdkVer": "2.4.2" },
    { "percentage": 3.88659439147e-7, "sdkVer": "2.4.1" },
    { "percentage": 0.000805108028192, "sdkVer": "2.4.0" },
    { "percentage": 0.0557186058555, "sdkVer": "2.3.2" },
    { "percentage": 3.88659439147e-7, "sdkVer": "2.3.1" },
    { "percentage": 0.000602033471238, "sdkVer": "2.3.0" },
    { "percentage": 0.088943158011, "sdkVer": "2.2.5" },
    { "percentage": 1.49633884071e-5, "sdkVer": "2.2.4" },
    { "percentage": 3.88659439147e-7, "sdkVer": "2.2.3" },
    { "percentage": 1.16597831744e-6, "sdkVer": "2.2.2" },
    { "percentage": 1.94329719573e-7, "sdkVer": "2.2.1" },
    { "percentage": 8.11326579219e-5, "sdkVer": "2.2.0" },
    { "percentage": 0.0123560665596, "sdkVer": "2.1.3" },
    { "percentage": 0.0434825378977, "sdkVer": "2.0.9" },
    { "percentage": 1.94329719573e-7, "sdkVer": "2.0.8" },
    { "percentage": 0.0434467812293, "sdkVer": "1.9.97" },
    { "percentage": 1.94329719573e-7, "sdkVer": "1.9.96" },
    { "percentage": 0.000342991955047, "sdkVer": "1.9.95" },
    { "percentage": 0.016828273561, "sdkVer": "1.9.9" },
    { "percentage": 1.94329719573e-7, "sdkVer": "1.9.8" },
    { "percentage": 0.000260984813387, "sdkVer": "1.9.6" },
    { "percentage": 0.00289114040295, "sdkVer": "1.9.4" },
    { "percentage": 5.8298915872e-7, "sdkVer": "1.9.2" },
    { "percentage": 0.000215705988726, "sdkVer": "1.7.4" },
    { "percentage": 0.000132532868749, "sdkVer": "1.7.3" },
    { "percentage": 0.000117958139781, "sdkVer": "1.6.8" },
    { "percentage": 3.51736792428e-5, "sdkVer": "1.6.6" },
    { "percentage": 6.21855102635e-6, "sdkVer": "1.6.3" },
    { "percentage": 7.94808553055e-5, "sdkVer": "1.5.8" },
    { "percentage": 0.000153326148743, "sdkVer": "1.4.4" },
    { "percentage": 1.94329719573e-5, "sdkVer": "1.3.0" },
    { "percentage": 0.000133893176786, "sdkVer": "1.2.5" },
    { "percentage": 7.38452934379e-6, "sdkVer": "1.2.4" },
    { "percentage": 0.00392060209239, "sdkVer": "1.1.1" },
    { "percentage": 0.000188402663126, "sdkVer": "1.0.1" }
  ],
  "relation": {
    "ios": [
      { "app": "7.0.9", "lib": "2.10.4" },
      { "app": "7.0.7", "lib": "2.9.5" },
      { "app": "7.0.5", "lib": "2.8.3" },
      { "app": "7.0.4", "lib": "2.7.7" },
      { "app": "7.0.3", "lib": "2.6.6" },
      { "app": "7.0.0", "lib": "2.5.2" },
      { "app": "6.7.3", "lib": "2.4.4" },
      { "app": "6.7.2", "lib": "2.3.2" },
      { "app": "6.7.0", "lib": "2.2.5" },
      { "app": "6.6.7", "lib": "2.1.3" },
      { "app": "6.6.6", "lib": "2.0.9" },
      { "app": "6.6.2", "lib": "2.5.0" },
      { "app": "6.6.2", "lib": "1.9.97" },
      { "app": "6.6.1", "lib": "1.9.9" },
      { "app": "6.6.0", "lib": "1.9.4" },
      { "app": "6.5.22", "lib": "1.7.4" },
      { "app": "6.5.16", "lib": "1.6.8" },
      { "app": "6.5.13", "lib": "1.5.8" },
      { "app": "6.5.10", "lib": "1.4.4" },
      { "app": "6.5.9", "lib": "1.3.0" },
      { "app": "6.5.8", "lib": "1.2.6" }
    ],
    "android": [
      { "app": "7.0.9", "lib": "2.10.4" },
      { "app": "7.0.7", "lib": "2.9.5" },
      { "app": "7.0.5", "lib": "2.8.3" },
      { "app": "7.0.4", "lib": "2.7.7" },
      { "app": "7.0.3", "lib": "2.6.6" },
      { "app": "7.0.0", "lib": "2.5.2" },
      { "app": "6.7.3", "lib": "2.4.4" },
      { "app": "6.7.2", "lib": "2.3.2" },
      { "app": "6.6.7", "lib": "2.2.5" },
      { "app": "6.6.6", "lib": "2.0.9" },
      { "app": "6.6.2", "lib": "1.9.97" },
      { "app": "6.6.1", "lib": "1.9.9" },
      { "app": "6.6.0", "lib": "1.9.4" },
      { "app": "6.5.22", "lib": "1.7.4" },
      { "app": "6.5.16", "lib": "1.6.8" },
      { "app": "6.5.13", "lib": "1.5.8" },
      { "app": "6.5.10", "lib": "1.4.4" },
      { "app": "6.5.8", "lib": "1.2.6" }
    ]
  }
}
